secret_checker/__init__.py
secret_checker/check_var.py
secret_checker-1.0.4.dist-info/METADATA
secret_checker-1.0.4.dist-info/WHEEL
secret_checker-1.0.4.dist-info/top_level.txt
secret_checker-1.0.4.dist-info/RECORD
